Metadata-Version: 2.1
Name: yw-distr
Version: 0.1
Summary: Gaussian and binomial distributions
Author: Youcheng Wang
